autometrics/__init__.py
autometrics/conftest.py
autometrics/constants.py
autometrics/decorator.py
autometrics/exemplar.py
autometrics/exposition.py
autometrics/initialization.py
autometrics/objectives.py
autometrics/prometheus_url.py
autometrics/py.typed
autometrics/settings.py
autometrics/test_caller.py
autometrics/test_decorator.py
autometrics/test_initialization.py
autometrics/test_objectives.py
autometrics/test_prometheus_url.py
autometrics/test_utils.py
autometrics/tracker/__init__.py
autometrics/tracker/opentelemetry.py
autometrics/tracker/prometheus.py
autometrics/tracker/temporary.py
autometrics/tracker/test_concurrency.py
autometrics/tracker/test_format.py
autometrics/tracker/test_tracker.py
autometrics/tracker/tracker.py
autometrics/tracker/types.py
autometrics/utils.py
foremetrics-2.0.0.dist-info/METADATA
foremetrics-2.0.0.dist-info/WHEEL
foremetrics-2.0.0.dist-info/licenses/LICENSE-APACHE
foremetrics-2.0.0.dist-info/licenses/LICENSE-MIT
foremetrics-2.0.0.dist-info/RECORD
