Metadata-Version: 2.4
Name: foremetrics
Version: 2.0.0
Summary: Easily add metrics to your system – and actually understand them using automatically customized Prometheus queries
License: MIT OR Apache-2.0
License-File: LICENSE-APACHE
License-File: LICENSE-MIT
Keywords: metrics,telemetry,prometheus,monitoring,observability,instrumentation,tracing
Author: Martin
Author-email: martin@foreai.co
Requires-Python: >=3.9,<4.0
Classifier: License :: Other/Proprietary License
Classifier: Programming Language :: Python :: 3
Classifier: Programming Language :: Python :: 3.9
Classifier: Programming Language :: Python :: 3.10
Classifier: Programming Language :: Python :: 3.11
Classifier: Programming Language :: Python :: 3.12
Classifier: Programming Language :: Python :: 3.13
Classifier: Programming Language :: Python :: 3.14
Classifier: Topic :: Software Development :: Build Tools
Classifier: Topic :: Software Development :: Libraries :: Python Modules
Classifier: Topic :: System :: Monitoring
Classifier: Typing :: Typed
Provides-Extra: exporter-otlp-proto-grpc
Provides-Extra: exporter-otlp-proto-http
Requires-Dist: opentelemetry-exporter-otlp-proto-grpc (>=1.20.0,<2.0.0) ; extra == "exporter-otlp-proto-grpc"
Requires-Dist: opentelemetry-exporter-otlp-proto-http (>=1.20.0,<2.0.0) ; extra == "exporter-otlp-proto-http"
Requires-Dist: opentelemetry-exporter-prometheus (==0.41b0)
Requires-Dist: opentelemetry-sdk (>=1.17.0,<2.0.0)
Requires-Dist: prometheus-client (>=0.16.0,<0.18.0)
Requires-Dist: pydantic (>=2.4.1,<3.0.0)
Requires-Dist: python-dotenv (>=1.0.0,<2.0.0)
Requires-Dist: typing-extensions (>=4.5.0,<5.0.0)
Project-URL: Homepage, https://github.com/foreai-co/autometrics-py
Project-URL: Repository, https://github.com/foreai-co/autometrics-py
